wpat/__init__.py
wpat/gui.py
wpat/main.py
wpat/scripts/__init__.py
wpat/scripts/cors_detector.py
wpat/scripts/html_report.py
wpat/scripts/login.py
wpat/scripts/plugin_scanner.py
wpat/scripts/rest_api_analyzer.py
wpat/scripts/security_txt.py
wpat/scripts/sensitive_files.py
wpat/scripts/ssl_checker.py
wpat/scripts/theme_scanner.py
wpat/scripts/user_enumeration.py
wpat/scripts/wordlists.py
wpat/scripts/wp_version.py
wpat/scripts/xmlrpc_analyzer.py
wpat-2.1.dist-info/METADATA
wpat-2.1.dist-info/WHEEL
wpat-2.1.dist-info/entry_points.txt
wpat-2.1.dist-info/top_level.txt
wpat-2.1.dist-info/RECORD
