Metadata-Version: 2.4
Name: wpat
Version: 2.1
Summary: WPAT (WordPress Professional Audit Tool) es una herramienta de auditoría de seguridad para WordPress que detecta vulnerabilidades comunes y expone riesgos de manera eficiente.
Home-page: https://github.com/Santitub/WPAT
Author: Santitub
Author-email: santitub22@email.com
License: GPLv3
Project-URL: Documentation, https://github.com/Santitub/wpat/wiki
Project-URL: Source, https://github.com/Santitub/wpat
Project-URL: Tracker, https://github.com/Santitub/wpat/issues
Keywords: wordpress security audit toolkit
Classifier: Development Status :: 5 - Production/Stable
Classifier: Intended Audience :: Information Technology
Classifier: Topic :: Security
Classifier: Operating System :: OS Independent
Classifier: License :: OSI Approved :: GNU General Public License v3 (GPLv3)
Classifier: Programming Language :: Python :: 3
Classifier: Programming Language :: Python :: 3.6
Classifier: Programming Language :: Python :: 3.11
Classifier: Programming Language :: Python :: 3.12
Requires-Python: >=3.6
Requires-Dist: colorama
Requires-Dist: requests
Requires-Dist: beautifulsoup4
Requires-Dist: tqdm
Requires-Dist: urllib3
Requires-Dist: jinja2
Provides-Extra: gui
Requires-Dist: pyqt5; extra == "gui"
Requires-Dist: PyQtWebEngine; extra == "gui"
Dynamic: author
Dynamic: author-email
Dynamic: classifier
Dynamic: description
Dynamic: description-content-type
Dynamic: home-page
Dynamic: keywords
Dynamic: license
Dynamic: project-url
Dynamic: provides-extra
Dynamic: requires-dist
Dynamic: requires-python
Dynamic: summary
